caf_fpga/__init__.py
caf_fpga/__version__.py
caf_fpga-0.0.1.dist-info/LICENSE
caf_fpga-0.0.1.dist-info/METADATA
caf_fpga-0.0.1.dist-info/WHEEL
caf_fpga-0.0.1.dist-info/top_level.txt
caf_fpga-0.0.1.dist-info/RECORD
