Metadata-Version: 2.1
Name: caf-fpga
Version: 0.0.1
Summary: CAF Verilog
Home-page: https://github.com/chiranthsiddappa/caf_fpga
Author: Chiranth Siddappa
Author-email: chiranthsiddappa@gmail.com
License: MIT
Platform: UNKNOWN
Requires-Python: >=3.4
Requires-Dist: caf-verilog
